linstor/__init__.py
linstor/config.py
linstor/errors.py
linstor/kv.py
linstor/linstorapi.py
linstor/properties.py
linstor/resource.py
linstor/resourcegroup.py
linstor/responses.py
linstor/sharedconsts.py
linstor/size_calc.py
linstor/version.py
python_linstor-1.27.1.dist-info/licenses/COPYING
python_linstor-1.27.1.dist-info/METADATA
python_linstor-1.27.1.dist-info/WHEEL
python_linstor-1.27.1.dist-info/top_level.txt
python_linstor-1.27.1.dist-info/RECORD
