Metadata-Version: 2.4
Name: python-linstor
Version: 1.27.1
Summary: Linstor python api
Home-page: https://www.linbit.com
Author-email: Rene Peinthor <rene.peinthor@linbit.com>, Roland Kammerer <roland.kammerer@linbit.com>, Gabor Hernadi <gabor.hernadi@linbit.com>, Moritz Wanzenboeck <moritz.wanzenboeck@linbit.com>
Maintainer-email: Rene Peinthor <rene.peinthor@linbit.com>
License-Expression: LGPL-3.0-or-later
Project-URL: Homepage, https://github.com/LINBIT/linstor-api-py
Project-URL: Documentation, https://linbit.github.io/linstor-api-py/
Project-URL: Repository, https://github.com/LINBIT/linstor-api-py.git
Project-URL: Issues, https://github.com/LINBIT/linstor-api-py/issues
Project-URL: Changelog, https://github.com/LINBIT/linstor-api-py/blob/master/CHANGELOG.md
Classifier: Development Status :: 5 - Production/Stable
Classifier: Intended Audience :: Developers
Classifier: Programming Language :: Python :: 2.7
Classifier: Programming Language :: Python :: 3.5
Classifier: Programming Language :: Python :: 3.6
Classifier: Programming Language :: Python :: 3.7
Classifier: Programming Language :: Python :: 3.8
Classifier: Programming Language :: Python :: 3.9
Classifier: Programming Language :: Python :: 3.10
Classifier: Programming Language :: Python :: 3.11
Classifier: Programming Language :: Python :: 3.12
Requires-Python: >=3.5
License-File: COPYING
Dynamic: home-page
Dynamic: license-file
